{
  "name": "earthquake",
  "display_name": "Earthquake",
  "city_name": "Lucknow Metro Area",
  "description": "7.2 magnitude earthquake. Building collapses across northern and central sectors.",
  "sectors": [
    { "id":"A1","name":"Aminabad","type":"commercial","row":0,"col":0,
      "polygon":[[26.8580,80.9180],[26.8580,80.9340],[26.8500,80.9340],[26.8500,80.9180]],
      "civilians":{"total":20,"critical":2,"stable":16,"rescued":2},"infrastructure":"damaged","hazards":["structural_collapse"],
      "resources_deployed":{"medical_teams":0,"rescue_units":0,"supply_caches":0} },
    { "id":"B1","name":"KGMU Hospital","type":"hospital","row":0,"col":1,
      "polygon":[[26.8580,80.9340],[26.8580,80.9500],[26.8500,80.9500],[26.8500,80.9340]],
      "civilians":{"total":45,"critical":12,"stable":30,"rescued":3},"infrastructure":"damaged","hazards":[],
      "resources_deployed":{"medical_teams":0,"rescue_units":0,"supply_caches":0} },
    { "id":"C1","name":"Lucknow University","type":"school","row":0,"col":2,
      "polygon":[[26.8580,80.9500],[26.8580,80.9660],[26.8500,80.9660],[26.8500,80.9500]],
      "civilians":{"total":60,"critical":18,"stable":38,"rescued":4},"infrastructure":"destroyed","hazards":["structural_collapse","fire"],
      "resources_deployed":{"medical_teams":0,"rescue_units":0,"supply_caches":0} },
    { "id":"D1","name":"Aishbagh","type":"industrial","row":0,"col":3,
      "polygon":[[26.8580,80.9660],[26.8580,80.9820],[26.8500,80.9820],[26.8500,80.9660]],
      "civilians":{"total":10,"critical":0,"stable":8,"rescued":2},"infrastructure":"damaged","hazards":["gas_leak"],
      "resources_deployed":{"medical_teams":0,"rescue_units":0,"supply_caches":0} },
    { "id":"A2","name":"Daliganj","type":"residential","row":1,"col":0,
      "polygon":[[26.8500,80.9180],[26.8500,80.9340],[26.8420,80.9340],[26.8420,80.9180]],
      "civilians":{"total":35,"critical":8,"stable":24,"rescued":3},"infrastructure":"damaged","hazards":["structural_collapse"],
      "resources_deployed":{"medical_teams":0,"rescue_units":0,"supply_caches":0} },
    { "id":"B2","name":"Hazratganj","type":"commercial","row":1,"col":1,
      "polygon":[[26.8500,80.9340],[26.8500,80.9500],[26.8420,80.9500],[26.8420,80.9340]],
      "civilians":{"total":25,"critical":3,"stable":20,"rescued":2},"infrastructure":"intact","hazards":[],
      "resources_deployed":{"medical_teams":0,"rescue_units":0,"supply_caches":0} },
    { "id":"C2","name":"Husainabad","type":"residential","row":1,"col":2,
      "polygon":[[26.8500,80.9500],[26.8500,80.9660],[26.8420,80.9660],[26.8420,80.9500]],
      "civilians":{"total":40,"critical":10,"stable":26,"rescued":4},"infrastructure":"damaged","hazards":["structural_collapse"],
      "resources_deployed":{"medical_teams":0,"rescue_units":0,"supply_caches":0} },
    { "id":"D2","name":"Charbagh","type":"residential","row":1,"col":3,
      "polygon":[[26.8500,80.9660],[26.8500,80.9820],[26.8420,80.9820],[26.8420,80.9660]],
      "civilians":{"total":30,"critical":5,"stable":22,"rescued":3},"infrastructure":"intact","hazards":[],
      "resources_deployed":{"medical_teams":0,"rescue_units":0,"supply_caches":0} },
    { "id":"A3","name":"Cantonment","type":"industrial","row":2,"col":0,
      "polygon":[[26.8420,80.9180],[26.8420,80.9340],[26.8340,80.9340],[26.8340,80.9180]],
      "civilians":{"total":12,"critical":0,"stable":11,"rescued":1},"infrastructure":"intact","hazards":[],
      "resources_deployed":{"medical_teams":0,"rescue_units":0,"supply_caches":0} },
    { "id":"B3","name":"Gomti Nagar","type":"residential","row":2,"col":1,
      "polygon":[[26.8420,80.9340],[26.8420,80.9500],[26.8340,80.9500],[26.8340,80.9340]],
      "civilians":{"total":50,"critical":6,"stable":38,"rescued":6},"infrastructure":"damaged","hazards":["flooding"],
      "resources_deployed":{"medical_teams":0,"rescue_units":0,"supply_caches":0} },
    { "id":"C3","name":"Alambagh","type":"residential","row":2,"col":2,
      "polygon":[[26.8420,80.9500],[26.8420,80.9660],[26.8340,80.9660],[26.8340,80.9500]],
      "civilians":{"total":28,"critical":4,"stable":22,"rescued":2},"infrastructure":"intact","hazards":[],
      "resources_deployed":{"medical_teams":0,"rescue_units":0,"supply_caches":0} },
    { "id":"D3","name":"Amausi","type":"industrial","row":2,"col":3,
      "polygon":[[26.8420,80.9660],[26.8420,80.9820],[26.8340,80.9820],[26.8340,80.9660]],
      "civilians":{"total":15,"critical":0,"stable":14,"rescued":1},"infrastructure":"intact","hazards":[],
      "resources_deployed":{"medical_teams":0,"rescue_units":0,"supply_caches":0} }
  ],
  "global_resources": { "medical_teams": 3, "rescue_units": 4, "supply_caches": 5 }
}
